{
  "schemaVersion": "1.0.0",
  "id": "getting-started",
  "title": "Getting started with Grafana",
  "description": "Learn the essentials: navigate the UI, connect your first data source, and build your first dashboard.",
  "guides": ["welcome-to-grafana", "prometheus-grafana-101", "first-dashboard"],
  "guideMetadata": {
    "welcome-to-grafana": { "title": "Welcome to Grafana", "estimatedMinutes": 5 },
    "prometheus-grafana-101": { "title": "Prometheus & Grafana 101", "estimatedMinutes": 10 },
    "first-dashboard": { "title": "Create your first dashboard", "estimatedMinutes": 10 }
  },
  "badgeId": "grafana-fundamentals",
  "targetPlatform": "oss",
  "estimatedMinutes": 25,
  "icon": "grafana"
}
